{
    "Number":  194,
    "Message":  "- Add outline to application icon\r\n- Remove duplicated log entries\r\n- Update LibreHardwareMonitorLib",
    "Checksums":  {
                      "FanControl_4_8":  "BAE361A34DFBB0D391717D4D59172861",
                      "FanControl_8_0":  "F7587B82EC048BA90B7C358C41D4340C",
                      "FanControl_4_8_Installer":  "22A98359AECA5A5BE5D3A7F6ABE69DE6",
                      "FanControl_8_0_Installer":  "C241EAC2A823A4DE227176DD457DB0BB",
                      "Updater":  "8BC3FB11C955E99E2EC5863884140484"
                  }
}
